{
  "CacheSourceKey": "13t7f6n",
  "CachePdfKey": "13t7f6n/13t7f6n-18um5om.pdf",
  "CacheXpzKey": "13t7f6n/13t7f6n-11aeo2y.xpz",
  "CacheInfoKey": "13t7f6n/13t7f6n-11aeo2y.json",
  "CacheCopyKey": null,
  "Document": "Type=FileSystem;File=No_Name.docx;Location=\"Type=Physical;Path=file\"",
  "DocumentFileName": "No_Name.docx",
  "DownloadFileName": null,
  "InputOptions": {
    "$type": "GleamTech.DocumentUltimate.WordProcessingInputOptions, GleamTech.DocumentUltimate",
    "FieldFileName": "No_Name.docx",
    "UpdateFields": true,
    "Encoding": null,
    "Format": "Docx",
    "Password": null
  },
  "PdfOutputOptions": {
    "Watermarks": [],
    "FastWebViewEnabled": false,
    "Password": null,
    "Attachments": [],
    "Format": "Pdf"
  },
  "XpzOutputOptions": {
    "Password": "13t7f6n",
    "HighQualityEnabled": false,
    "Format": "Xpz"
  },
  "Attachments": []
}